[
    { "category": "Abap", "value": 0.34, "color": "#FF5733" },
    { "category": "Ada", "value": 0.36, "color": "#33FF57" },
    { "category": "C/C++", "value": 10.01, "color": "green" },
    { "category": "C#", "value": 4.68, "color": "#3357FF" },
    { "category": "Cobol", "value": 0.42, "color": "#FFC300" },
    { "category": "Dart", "value": 0.0, "color": "#FF33A1" },
    { "category": "Delphi/Pascal", "value": 2.8, "color": "#33FFF6" },
    { "category": "Go", "value": 0.0, "color": "#FF8C33" },
    { "category": "Groovy", "value": 0.03, "color": "#A133FF" },
    { "category": "Haskell", "value": 0.22, "color": "#33A1FF" },
    { "category": "Java", "value": 30.16, "color": "red" },
    { "category": "JavaScript", "value": 8.59, "color": "#FFD700" },
    { "category": "Julia", "value": 0.0, "color": "#FF33B5" },
    { "category": "Kotlin", "value": 0.24, "color": "#33FF99" },
    { "category": "Lua", "value": 0.16, "color": "#FF3380" },
    { "category": "Matlab", "value": 2.1, "color": "#B533FF" },
    { "category": "Objective-C", "value": 0.19, "color": "#33FFDD" },
    { "category": "Perl", "value": 7.33, "color": "#FFC1C1" },
    { "category": "PHP", "value": 18.62, "color": "#FF6F33" },
    { "category": "Powershell", "value": 0.16, "color": "#8C33FF" },
    { "category": "Python", "value": 2.51, "color": "blue" },
    { "category": "R", "value": 0.39, "color": "#3399FF" },
    { "category": "Ruby", "value": 0.33, "color": "#FF3333" },
    { "category": "Rust", "value": 0.24, "color": "#FF5733" },
    { "category": "Scala", "value": 0.17, "color": "#33FFB5" },
    { "category": "Swift", "value": 0.0, "color": "#FF33F6" },
    { "category": "TypeScript", "value": 0.0, "color": "#33FF80" },
    { "category": "VBA", "value": 1.43, "color": "#FFC333" },
    { "category": "Visual Basic", "value": 8.5, "color": "#A1FF33" }
  ]
